{
  "main": {
    "id": "63b533bfb6001254",
    "type": "split",
    "children": [
      {
        "id": "9d19aa24b0fc45a2",
        "type": "tabs",
        "children": [
          {
            "id": "3b2cd0c33684b0b3",
            "type": "leaf",
            "state": {
              "type": "markdown",
              "state": {
                "file": "projects/my_wiki/linux/venv/venv.md",
                "mode": "preview",
                "source": true
              }
            }
          }
        ]
      }
    ],
    "direction": "vertical"
  },
  "left": {
    "id": "6ccdf6c703576ce9",
    "type": "split",
    "children": [
      {
        "id": "6dfd3e4adbd3ce56",
        "type": "tabs",
        "children": [
          {
            "id": "c823dcdcd01a180a",
            "type": "leaf",
            "state": {
              "type": "search",
              "state": {
                "query": "",
                "matchingCase": false,
                "explainSearch": false,
                "collapseAll": false,
                "extraContext": false,
                "sortOrder": "alphabetical"
              }
            }
          },
          {
            "id": "61331d656e335dc3",
            "type": "leaf",
            "state": {
              "type": "bookmarks",
              "state": {}
            }
          },
          {
            "id": "fd3393ea14f0c64a",
            "type": "leaf",
            "state": {
              "type": "file-explorer",
              "state": {
                "sortOrder": "byModifiedTimeReverse"
              }
            }
          }
        ],
        "currentTab": 2
      }
    ],
    "direction": "horizontal",
    "width": 200
  },
  "right": {
    "id": "accc9149a39693cc",
    "type": "split",
    "children": [
      {
        "id": "443d2b7bad5d61c1",
        "type": "tabs",
        "children": [
          {
            "id": "ef62255bfc678715",
            "type": "leaf",
            "state": {
              "type": "backlink",
              "state": {
                "file": "projects/my_wiki/linux/venv/venv.md",
                "collapseAll": true,
                "extraContext": true,
                "sortOrder": "alphabetical",
                "showSearch": false,
                "searchQuery": "",
                "backlinkCollapsed": false,
                "unlinkedCollapsed": true
              }
            }
          },
          {
            "id": "28c02bec70ff92b7",
            "type": "leaf",
            "state": {
              "type": "outgoing-link",
              "state": {
                "file": "projects/my_wiki/linux/venv/venv.md",
                "linksCollapsed": false,
                "unlinkedCollapsed": false
              }
            }
          },
          {
            "id": "6562b620e5ecdd9a",
            "type": "leaf",
            "state": {
              "type": "tag",
              "state": {
                "sortOrder": "frequency",
                "useHierarchy": false
              }
            }
          },
          {
            "id": "638124ce113818d5",
            "type": "leaf",
            "state": {
              "type": "outline",
              "state": {
                "file": "projects/my_wiki/linux/venv/venv.md"
              }
            }
          },
          {
            "id": "890161027c7aee51",
            "type": "leaf",
            "state": {
              "type": "advanced-tables-toolbar",
              "state": {}
            }
          }
        ],
        "currentTab": 2
      }
    ],
    "direction": "horizontal",
    "width": 375.5,
    "collapsed": true
  },
  "left-ribbon": {
    "hiddenItems": {
      "switcher:Меню быстрого перехода": false,
      "canvas:Создать новый холст": false,
      "daily-notes:Сегодняшняя заметка": false,
      "templates:Вставить шаблон": false,
      "command-palette:Открыть палитру команд": false,
      "markdown-importer:Импорт Markdown-файлов": false,
      "graph:Граф": false,
      "table-editor-obsidian:Advanced Tables Toolbar": false
    }
  },
  "active": "3b2cd0c33684b0b3",
  "lastOpenFiles": [
    "About.md",
    "Без названия.canvas",
    "projects/my_wiki/linux/sudo/sudo.md",
    "projects/my_wiki/devops/git/git.md",
    "projects/my_wiki/web/django/install_django/install_django.md",
    "README.md",
    "docs.md",
    "index.md",
    "Без названия/Drawing 2024-05-07 18.20.05.excalidraw.md",
    "Без названия",
    "templaits/new_doc.md",
    "Excalidraw/Drawing 2024-05-07 18.13.13.excalidraw.md",
    "projects/my_wiki/devops/docker/docker-compose/Docker compose.md",
    "Excalidraw",
    "Без названия.md",
    "templaits/Без названия.md",
    "_config.yml",
    "_config.yml.md",
    "projects/my_wiki/linux/system_initialization/systemd/python_script_service.md",
    "projects/my_wiki/linux/sudo/files/install_sudo.png",
    "projects/my_wiki/linux/sudo/files",
    "project/my_wiki/devops.md",
    "project/my_wiki",
    "project",
    "Devops.md",
    "projects/my_wiki/python/variable_types/dictress/dictress.md",
    "projects/my_wiki/python/function/default_function.md",
    "projects/dusky-wiki/python/function/default_function.md",
    "projects/my_wiki/python/function/lambda.md",
    "projects/dusky-wiki/python/function",
    "projects/dusky-wiki/python",
    "projects/dusky-wiki",
    "projects/my_wiki/python/function/comprehensions.md",
    "projects/my_wiki/python/function/decorators.md",
    "projects/my_wiki/python/files/files.md",
    "projects/my_wiki/python/class/mixin_class.md",
    "projects/my_wiki/devops/git",
    "projects/my_wiki/devops/docker/docker-compose/files/1.png",
    "projects/dusky-wiki/linux/docker/docker-compose/2.png",
    "projects/dusky-wiki/linux/docker/docker-compose/1.png",
    "projects/dusky-wiki/network/mikrotik/vrrp/mikro.png",
    "projects/dusky-wiki/network/mikrotik/vrrp/VRRP.jpg",
    "projects/dusky-wiki/linux/docker/docker-compose/10.png",
    "projects/dusky-wiki/linux/docker/docker-compose/9.png",
    "projects/dusky-wiki/linux/docker/docker-compose/8.png",
    "projects/dusky-wiki/linux/docker/docker-compose/7.png",
    "devops/Без названия.canvas"
  ]
}